argame/__init__.py
argame/argame.py
argaming-1.0.0.dist-info/LICENSE
argaming-1.0.0.dist-info/METADATA
argaming-1.0.0.dist-info/WHEEL
argaming-1.0.0.dist-info/top_level.txt
argaming-1.0.0.dist-info/RECORD
