Metadata-Version: 2.1
Name: argaming
Version: 1.0.0
Summary: This framework help you creating AR gaming three times faster, easer and cost effective
Home-page: https://ARGaming.GrowUpInfo.com
Author: GrowUp Tech Solutions
Author-email: DevShahmirKhan@gmail.com
License: UNKNOWN
Project-URL: Bug Tracker, https://github.com/pypa/sampleproject/issues
Platform: UNKNOWN
Classifier: Programming Language :: Python :: 3
Classifier: License :: OSI Approved :: MIT License
Classifier: Operating System :: OS Independent
Requires-Python: >=3.6
License-File: LICENSE
